setup.py
tornask/__init__.py
tornask/manager.py
tornask.egg-info/PKG-INFO
tornask.egg-info/SOURCES.txt
tornask.egg-info/dependency_links.txt
tornask.egg-info/top_level.txt
tornask.egg-info/zip-safe