Metadata-Version: 1.1
Name: tornask
Version: 1.2
Summary: tornask is a task manager based on tornado
Home-page: https://github.com/mqingyn/tornask
Author: mqingyn
Author-email: mqingyn@gmail.com
License: BSD
Keywords: python tornask tornado
Platform: UNKNOWN
Requires: tornado
Requires: futures
